magic_carpet/__init__.py
magic_carpet/carpet_client.py
magic_carpet/common/container.py
magic_carpet/evaluators/__init__.py
magic_carpet/evaluators/eval_containers.py
magic_carpet/evaluators/evaluator.py
magic_carpet/models/__init__.py
magic_carpet/models/model.py
magic_carpet/models/model_containers.py
magic_carpet/routers/__init__.py
magic_carpet/routers/cascade_router.py
magic_carpet/routers/model_map_router.py
magic_carpet/routers/nn_router.py
magic_carpet/routers/router.py
magic_carpet/utils.py
magic_carpet-0.2.0.dist-info/LICENSE
magic_carpet-0.2.0.dist-info/METADATA
magic_carpet-0.2.0.dist-info/WHEEL
magic_carpet-0.2.0.dist-info/RECORD
