Metadata-Version: 2.1
Name: magic-carpet
Version: 0.2.0
Summary: Model router for ML systems
Author: Sidhart Krishnan
Author-email: sidhartkrishnan@gmail.com
Requires-Python: >=3.11,<4.0
Classifier: Programming Language :: Python :: 3
Classifier: Programming Language :: Python :: 3.11
Classifier: Programming Language :: Python :: 3.12
Requires-Dist: requests (>=2.31.0,<3.0.0)
